smart_tsp_benchmark/__init__.py
smart_tsp_benchmark/tsp_benchmark.py
smart_tsp_benchmark/calculators/__init__.py
smart_tsp_benchmark/calculators/length.py
smart_tsp_benchmark/generators/__init__.py
smart_tsp_benchmark/generators/points.py
smart_tsp_benchmark/optimizers/__init__.py
smart_tsp_benchmark/optimizers/fast_opt.py
smart_tsp_benchmark/optimizers/two_opt.py
smart_tsp_benchmark/visualization/__init__.py
smart_tsp_benchmark/visualization/plot_routes.py
smart_tsp_benchmark-1.0.0.dist-info/licenses/LICENSE
smart_tsp_benchmark-1.0.0.dist-info/METADATA
smart_tsp_benchmark-1.0.0.dist-info/WHEEL
smart_tsp_benchmark-1.0.0.dist-info/top_level.txt
smart_tsp_benchmark-1.0.0.dist-info/RECORD
