Metadata-Version: 2.4
Name: smart-tsp-benchmark
Version: 1.0.0
Summary: Smart TSP Benchmark is a professional algorithm testing infrastructure with customizable scenarios and detailed metrics.
Author-email: "A.A Suvorov" <smartlegiondev@gmail.com>
License-Expression: BSD-3-Clause
Project-URL: Homepage, https://github.com/smartlegionlab/smart-tsp-benchmark
Classifier: Programming Language :: Python :: 3
Classifier: Operating System :: OS Independent
Requires-Python: >=3.6
License-File: LICENSE
Requires-Dist: contourpy==1.3.2
Requires-Dist: cycler==0.12.1
Requires-Dist: fonttools==4.58.5
Requires-Dist: kiwisolver==1.4.8
Requires-Dist: matplotlib==3.10.3
Requires-Dist: numpy==2.2.6
Requires-Dist: packaging==25.0
Requires-Dist: pillow==11.3.0
Requires-Dist: pyparsing==3.2.3
Requires-Dist: python-dateutil==2.9.0.post0
Requires-Dist: scipy==1.16.0
Requires-Dist: six==1.17.0
Dynamic: license-file
